{
	"nGPUPerNode": 4,
	"nNode": 1,
	"tasks": [
		{
			"type": "computation",
			"opid": 0,
			"op": "conv1",
			"part": 0,
			"guid": 0,
			"workerId": 0,
			"counter": 0,
			"readyTime": 0.000000,
			"startTime": 0.000000,
			"computeTime": 11.302144
		}, 
		{
			"type": "computation",
			"opid": 0,
			"op": "conv1",
			"part": 1,
			"guid": 1,
			"workerId": 2,
			"counter": 0,
			"readyTime": 0.000000,
			"startTime": 0.000000,
			"computeTime": 11.302144
		}, 
		{
			"type": "computation",
			"opid": 0,
			"op": "conv1",
			"part": 2,
			"guid": 2,
			"workerId": 3,
			"counter": 0,
			"readyTime": 0.000000,
			"startTime": 0.000000,
			"computeTime": 11.302144
		}, 
		{
			"type": "computation",
			"opid": 0,
			"op": "conv1",
			"part": 3,
			"guid": 3,
			"workerId": 1,
			"counter": 0,
			"readyTime": 0.000000,
			"startTime": 0.000000,
			"computeTime": 11.302144
		}, 
		{
			"type": "computation",
			"opid": 1,
			"op": "pool2",
			"part": 0,
			"guid": 4,
			"workerId": 0,
			"counter": 1,
			"readyTime": 11.302144,
			"startTime": 11.302144,
			"computeTime": 1.512128
		}, 
		{
			"type": "computation",
			"opid": 1,
			"op": "pool2",
			"part": 1,
			"guid": 5,
			"workerId": 2,
			"counter": 1,
			"readyTime": 11.302144,
			"startTime": 11.302144,
			"computeTime": 1.512128
		}, 
		{
			"type": "computation",
			"opid": 1,
			"op": "pool2",
			"part": 2,
			"guid": 6,
			"workerId": 3,
			"counter": 1,
			"readyTime": 11.302144,
			"startTime": 11.302144,
			"computeTime": 1.512128
		}, 
		{
			"type": "computation",
			"opid": 1,
			"op": "pool2",
			"part": 3,
			"guid": 7,
			"workerId": 1,
			"counter": 1,
			"readyTime": 11.302144,
			"startTime": 11.302144,
			"computeTime": 1.512128
		}, 
		{
			"type": "computation",
			"opid": 2,
			"op": "conv3",
			"part": 0,
			"guid": 8,
			"workerId": 3,
			"counter": 1,
			"readyTime": 15.203059,
			"startTime": 15.203059,
			"computeTime": 6.667000
		}, 
		{
			"type": "computation",
			"opid": 2,
			"op": "conv3",
			"part": 1,
			"guid": 9,
			"workerId": 0,
			"counter": 1,
			"readyTime": 15.203059,
			"startTime": 15.203059,
			"computeTime": 6.667000
		}, 
		{
			"type": "computation",
			"opid": 2,
			"op": "conv3",
			"part": 2,
			"guid": 10,
			"workerId": 2,
			"counter": 1,
			"readyTime": 15.203059,
			"startTime": 15.203059,
			"computeTime": 6.667000
		}, 
		{
			"type": "computation",
			"opid": 2,
			"op": "conv3",
			"part": 3,
			"guid": 11,
			"workerId": 1,
			"counter": 1,
			"readyTime": 12.814272,
			"startTime": 12.814272,
			"computeTime": 6.667000
		}, 
		{
			"type": "computation",
			"opid": 3,
			"op": "pool4",
			"part": 0,
			"guid": 15,
			"workerId": 3,
			"counter": 1,
			"readyTime": 21.870060,
			"startTime": 21.870060,
			"computeTime": 0.993792
		}, 
		{
			"type": "computation",
			"opid": 3,
			"op": "pool4",
			"part": 1,
			"guid": 16,
			"workerId": 2,
			"counter": 1,
			"readyTime": 29.036423,
			"startTime": 29.036423,
			"computeTime": 0.993792
		}, 
		{
			"type": "computation",
			"opid": 3,
			"op": "pool4",
			"part": 2,
			"guid": 17,
			"workerId": 2,
			"counter": 1,
			"readyTime": 21.870060,
			"startTime": 21.870060,
			"computeTime": 0.993792
		}, 
		{
			"type": "computation",
			"opid": 3,
			"op": "pool4",
			"part": 3,
			"guid": 18,
			"workerId": 3,
			"counter": 1,
			"readyTime": 26.647633,
			"startTime": 26.647633,
			"computeTime": 0.993792
		}, 
		{
			"type": "computation",
			"opid": 4,
			"op": "conv5",
			"part": 0,
			"guid": 21,
			"workerId": 1,
			"counter": 1,
			"readyTime": 24.525188,
			"startTime": 24.525188,
			"computeTime": 6.631904
		}, 
		{
			"type": "computation",
			"opid": 4,
			"op": "conv5",
			"part": 1,
			"guid": 22,
			"workerId": 0,
			"counter": 1,
			"readyTime": 31.691551,
			"startTime": 31.691551,
			"computeTime": 6.631904
		}, 
		{
			"type": "computation",
			"opid": 4,
			"op": "conv5",
			"part": 2,
			"guid": 23,
			"workerId": 0,
			"counter": 1,
			"readyTime": 24.525188,
			"startTime": 24.525188,
			"computeTime": 6.631904
		}, 
		{
			"type": "computation",
			"opid": 4,
			"op": "conv5",
			"part": 3,
			"guid": 24,
			"workerId": 2,
			"counter": 1,
			"readyTime": 29.302761,
			"startTime": 30.030214,
			"computeTime": 6.631904
		}, 
		{
			"type": "computation",
			"opid": 5,
			"op": "conv6",
			"part": 0,
			"guid": 29,
			"workerId": 3,
			"counter": 1,
			"readyTime": 34.479767,
			"startTime": 34.479767,
			"computeTime": 7.714560
		}, 
		{
			"type": "computation",
			"opid": 5,
			"op": "conv6",
			"part": 1,
			"guid": 30,
			"workerId": 2,
			"counter": 1,
			"readyTime": 41.646130,
			"startTime": 44.376678,
			"computeTime": 7.714560
		}, 
		{
			"type": "computation",
			"opid": 5,
			"op": "conv6",
			"part": 2,
			"guid": 31,
			"workerId": 2,
			"counter": 1,
			"readyTime": 34.479767,
			"startTime": 36.662117,
			"computeTime": 7.714560
		}, 
		{
			"type": "computation",
			"opid": 5,
			"op": "conv6",
			"part": 3,
			"guid": 32,
			"workerId": 3,
			"counter": 1,
			"readyTime": 39.984791,
			"startTime": 42.194328,
			"computeTime": 7.714560
		}, 
		{
			"type": "computation",
			"opid": 6,
			"op": "conv7",
			"part": 0,
			"guid": 37,
			"workerId": 1,
			"counter": 1,
			"readyTime": 44.409447,
			"startTime": 44.409447,
			"computeTime": 5.586944
		}, 
		{
			"type": "computation",
			"opid": 6,
			"op": "conv7",
			"part": 1,
			"guid": 38,
			"workerId": 0,
			"counter": 1,
			"readyTime": 54.306358,
			"startTime": 54.306358,
			"computeTime": 5.586944
		}, 
		{
			"type": "computation",
			"opid": 6,
			"op": "conv7",
			"part": 2,
			"guid": 39,
			"workerId": 3,
			"counter": 1,
			"readyTime": 46.591797,
			"startTime": 49.908890,
			"computeTime": 5.586944
		}, 
		{
			"type": "computation",
			"opid": 6,
			"op": "conv7",
			"part": 3,
			"guid": 40,
			"workerId": 1,
			"counter": 1,
			"readyTime": 52.124008,
			"startTime": 52.124008,
			"computeTime": 5.586944
		}, 
		{
			"type": "computation",
			"opid": 7,
			"op": "pool8",
			"part": 0,
			"guid": 45,
			"workerId": 0,
			"counter": 2,
			"readyTime": 59.893303,
			"startTime": 59.893303,
			"computeTime": 0.915696
		}, 
		{
			"type": "computation",
			"opid": 7,
			"op": "pool8",
			"part": 1,
			"guid": 46,
			"workerId": 1,
			"counter": 2,
			"readyTime": 57.710953,
			"startTime": 57.710953,
			"computeTime": 0.915696
		}, 
		{
			"type": "computation",
			"opid": 8,
			"op": "flat",
			"part": 0,
			"guid": 49,
			"workerId": 0,
			"counter": 1,
			"readyTime": 60.808998,
			"startTime": 60.808998,
			"computeTime": 0.000000
		}, 
		{
			"type": "computation",
			"opid": 8,
			"op": "flat",
			"part": 1,
			"guid": 50,
			"workerId": 0,
			"counter": 1,
			"readyTime": 60.808998,
			"startTime": 60.808998,
			"computeTime": 0.000000
		}, 
		{
			"type": "computation",
			"opid": 8,
			"op": "flat",
			"part": 2,
			"guid": 51,
			"workerId": 0,
			"counter": 1,
			"readyTime": 59.098507,
			"startTime": 59.893303,
			"computeTime": 0.000000
		}, 
		{
			"type": "computation",
			"opid": 8,
			"op": "flat",
			"part": 3,
			"guid": 52,
			"workerId": 0,
			"counter": 1,
			"readyTime": 59.098507,
			"startTime": 59.893303,
			"computeTime": 0.000000
		}, 
		{
			"type": "computation",
			"opid": 9,
			"op": "linear9",
			"part": 0,
			"guid": 55,
			"workerId": 0,
			"counter": 4,
			"readyTime": 60.808998,
			"startTime": 60.808998,
			"computeTime": 3.877376
		}, 
		{
			"type": "computation",
			"opid": 9,
			"op": "linear9",
			"part": 1,
			"guid": 56,
			"workerId": 3,
			"counter": 4,
			"readyTime": 61.280857,
			"startTime": 61.280857,
			"computeTime": 3.877376
		}, 
		{
			"type": "computation",
			"opid": 9,
			"op": "linear9",
			"part": 2,
			"guid": 57,
			"workerId": 1,
			"counter": 4,
			"readyTime": 61.280857,
			"startTime": 61.280857,
			"computeTime": 3.877376
		}, 
		{
			"type": "computation",
			"opid": 9,
			"op": "linear9",
			"part": 3,
			"guid": 58,
			"workerId": 2,
			"counter": 4,
			"readyTime": 61.280857,
			"startTime": 61.280857,
			"computeTime": 3.877376
		}, 
		{
			"type": "computation",
			"opid": 10,
			"op": "linear10",
			"part": 0,
			"guid": 71,
			"workerId": 0,
			"counter": 4,
			"readyTime": 65.367950,
			"startTime": 65.367950,
			"computeTime": 1.634272
		}, 
		{
			"type": "computation",
			"opid": 10,
			"op": "linear10",
			"part": 1,
			"guid": 72,
			"workerId": 2,
			"counter": 4,
			"readyTime": 65.367950,
			"startTime": 65.367950,
			"computeTime": 1.634272
		}, 
		{
			"type": "computation",
			"opid": 10,
			"op": "linear10",
			"part": 2,
			"guid": 73,
			"workerId": 1,
			"counter": 4,
			"readyTime": 65.367950,
			"startTime": 65.367950,
			"computeTime": 1.634272
		}, 
		{
			"type": "computation",
			"opid": 10,
			"op": "linear10",
			"part": 3,
			"guid": 74,
			"workerId": 3,
			"counter": 4,
			"readyTime": 65.367950,
			"startTime": 65.367950,
			"computeTime": 1.634272
		}, 
		{
			"type": "computation",
			"opid": 11,
			"op": "linear11",
			"part": 0,
			"guid": 87,
			"workerId": 3,
			"counter": 4,
			"readyTime": 67.211937,
			"startTime": 67.211937,
			"computeTime": 0.482744
		}, 
		{
			"type": "computation",
			"opid": 11,
			"op": "linear11",
			"part": 1,
			"guid": 88,
			"workerId": 2,
			"counter": 4,
			"readyTime": 67.211937,
			"startTime": 67.211937,
			"computeTime": 0.482744
		}, 
		{
			"type": "computation",
			"opid": 11,
			"op": "linear11",
			"part": 2,
			"guid": 89,
			"workerId": 2,
			"counter": 4,
			"readyTime": 67.211937,
			"startTime": 67.694679,
			"computeTime": 0.482744
		}, 
		{
			"type": "computation",
			"opid": 11,
			"op": "linear11",
			"part": 3,
			"guid": 90,
			"workerId": 1,
			"counter": 4,
			"readyTime": 67.211937,
			"startTime": 67.211937,
			"computeTime": 0.482744
		}, 
		{
			"type": "intra-communication",
			"node":0,
			"commid": 0,
			"fromWorker": 0,
			"toWorker": 3,
			"fromTask": 4,
			"toTask": 8,
			"xferSize": 11943936.000000,
			"workerId": 64,
			"guid": 12,
			"counter": 1,
			"readyTime": 12.814272,
			"startTime": 12.814272,
			"computeTime": 2.388787
		}, 
		{
			"type": "intra-communication",
			"node":0,
			"commid": 1,
			"fromWorker": 2,
			"toWorker": 0,
			"fromTask": 5,
			"toTask": 9,
			"xferSize": 11943936.000000,
			"workerId": 129,
			"guid": 13,
			"counter": 1,
			"readyTime": 12.814272,
			"startTime": 12.814272,
			"computeTime": 2.388787
		}, 
		{
			"type": "intra-communication",
			"node":0,
			"commid": 2,
			"fromWorker": 3,
			"toWorker": 2,
			"fromTask": 6,
			"toTask": 10,
			"xferSize": 11943936.000000,
			"workerId": 194,
			"guid": 14,
			"counter": 1,
			"readyTime": 12.814272,
			"startTime": 12.814272,
			"computeTime": 2.388787
		}, 
		{
			"type": "intra-communication",
			"node":0,
			"commid": 3,
			"fromWorker": 0,
			"toWorker": 2,
			"fromTask": 9,
			"toTask": 16,
			"xferSize": 35831808.000000,
			"workerId": 129,
			"guid": 19,
			"counter": 1,
			"readyTime": 21.870060,
			"startTime": 21.870060,
			"computeTime": 7.166362
		}, 
		{
			"type": "intra-communication",
			"node":0,
			"commid": 4,
			"fromWorker": 1,
			"toWorker": 3,
			"fromTask": 11,
			"toTask": 18,
			"xferSize": 35831808.000000,
			"workerId": 259,
			"guid": 20,
			"counter": 1,
			"readyTime": 19.481272,
			"startTime": 19.481272,
			"computeTime": 7.166362
		}, 
		{
			"type": "intra-communication",
			"node":0,
			"commid": 5,
			"fromWorker": 3,
			"toWorker": 1,
			"fromTask": 15,
			"toTask": 21,
			"xferSize": 8306688.000000,
			"workerId": 64,
			"guid": 25,
			"counter": 1,
			"readyTime": 22.863852,
			"startTime": 22.863852,
			"computeTime": 1.661338
		}, 
		{
			"type": "intra-communication",
			"node":0,
			"commid": 6,
			"fromWorker": 2,
			"toWorker": 0,
			"fromTask": 16,
			"toTask": 22,
			"xferSize": 8306688.000000,
			"workerId": 129,
			"guid": 26,
			"counter": 1,
			"readyTime": 30.030214,
			"startTime": 30.030214,
			"computeTime": 1.661338
		}, 
		{
			"type": "intra-communication",
			"node":0,
			"commid": 7,
			"fromWorker": 2,
			"toWorker": 0,
			"fromTask": 17,
			"toTask": 23,
			"xferSize": 8306688.000000,
			"workerId": 194,
			"guid": 27,
			"counter": 1,
			"readyTime": 22.863852,
			"startTime": 22.863852,
			"computeTime": 1.661338
		}, 
		{
			"type": "intra-communication",
			"node":0,
			"commid": 8,
			"fromWorker": 3,
			"toWorker": 2,
			"fromTask": 18,
			"toTask": 24,
			"xferSize": 8306688.000000,
			"workerId": 259,
			"guid": 28,
			"counter": 1,
			"readyTime": 27.641424,
			"startTime": 27.641424,
			"computeTime": 1.661338
		}, 
		{
			"type": "intra-communication",
			"node":0,
			"commid": 9,
			"fromWorker": 1,
			"toWorker": 3,
			"fromTask": 21,
			"toTask": 29,
			"xferSize": 16613376.000000,
			"workerId": 64,
			"guid": 33,
			"counter": 1,
			"readyTime": 31.157093,
			"startTime": 31.157093,
			"computeTime": 3.322675
		}, 
		{
			"type": "intra-communication",
			"node":0,
			"commid": 10,
			"fromWorker": 0,
			"toWorker": 2,
			"fromTask": 22,
			"toTask": 30,
			"xferSize": 16613376.000000,
			"workerId": 129,
			"guid": 34,
			"counter": 1,
			"readyTime": 38.323456,
			"startTime": 38.323456,
			"computeTime": 3.322675
		}, 
		{
			"type": "intra-communication",
			"node":0,
			"commid": 11,
			"fromWorker": 0,
			"toWorker": 2,
			"fromTask": 23,
			"toTask": 31,
			"xferSize": 16613376.000000,
			"workerId": 194,
			"guid": 35,
			"counter": 1,
			"readyTime": 31.157093,
			"startTime": 31.157093,
			"computeTime": 3.322675
		}, 
		{
			"type": "intra-communication",
			"node":0,
			"commid": 12,
			"fromWorker": 2,
			"toWorker": 3,
			"fromTask": 24,
			"toTask": 32,
			"xferSize": 16613376.000000,
			"workerId": 259,
			"guid": 36,
			"counter": 1,
			"readyTime": 36.662117,
			"startTime": 36.662117,
			"computeTime": 3.322675
		}, 
		{
			"type": "intra-communication",
			"node":0,
			"commid": 13,
			"fromWorker": 3,
			"toWorker": 1,
			"fromTask": 29,
			"toTask": 37,
			"xferSize": 11075584.000000,
			"workerId": 64,
			"guid": 41,
			"counter": 1,
			"readyTime": 42.194328,
			"startTime": 42.194328,
			"computeTime": 2.215117
		}, 
		{
			"type": "intra-communication",
			"node":0,
			"commid": 14,
			"fromWorker": 2,
			"toWorker": 0,
			"fromTask": 30,
			"toTask": 38,
			"xferSize": 11075584.000000,
			"workerId": 129,
			"guid": 42,
			"counter": 1,
			"readyTime": 52.091240,
			"startTime": 52.091240,
			"computeTime": 2.215117
		}, 
		{
			"type": "intra-communication",
			"node":0,
			"commid": 15,
			"fromWorker": 2,
			"toWorker": 3,
			"fromTask": 31,
			"toTask": 39,
			"xferSize": 11075584.000000,
			"workerId": 194,
			"guid": 43,
			"counter": 1,
			"readyTime": 44.376678,
			"startTime": 44.376678,
			"computeTime": 2.215117
		}, 
		{
			"type": "intra-communication",
			"node":0,
			"commid": 16,
			"fromWorker": 3,
			"toWorker": 1,
			"fromTask": 32,
			"toTask": 40,
			"xferSize": 11075584.000000,
			"workerId": 259,
			"guid": 44,
			"counter": 1,
			"readyTime": 49.908890,
			"startTime": 49.908890,
			"computeTime": 2.215117
		}, 
		{
			"type": "intra-communication",
			"node":0,
			"commid": 17,
			"fromWorker": 1,
			"toWorker": 0,
			"fromTask": 37,
			"toTask": 45,
			"xferSize": 11075584.000000,
			"workerId": 64,
			"guid": 47,
			"counter": 1,
			"readyTime": 49.996391,
			"startTime": 49.996391,
			"computeTime": 2.215117
		}, 
		{
			"type": "intra-communication",
			"node":0,
			"commid": 18,
			"fromWorker": 3,
			"toWorker": 1,
			"fromTask": 39,
			"toTask": 46,
			"xferSize": 11075584.000000,
			"workerId": 193,
			"guid": 48,
			"counter": 1,
			"readyTime": 55.495834,
			"startTime": 55.495834,
			"computeTime": 2.215117
		}, 
		{
			"type": "intra-communication",
			"node":0,
			"commid": 19,
			"fromWorker": 1,
			"toWorker": 0,
			"fromTask": 46,
			"toTask": 51,
			"xferSize": 2359296.000000,
			"workerId": 130,
			"guid": 53,
			"counter": 1,
			"readyTime": 58.626648,
			"startTime": 58.626648,
			"computeTime": 0.471859
		}, 
		{
			"type": "intra-communication",
			"node":0,
			"commid": 20,
			"fromWorker": 1,
			"toWorker": 0,
			"fromTask": 46,
			"toTask": 52,
			"xferSize": 2359296.000000,
			"workerId": 131,
			"guid": 54,
			"counter": 1,
			"readyTime": 58.626648,
			"startTime": 58.626648,
			"computeTime": 0.471859
		}, 
		{
			"type": "intra-communication",
			"node":0,
			"commid": 21,
			"fromWorker": 0,
			"toWorker": 3,
			"fromTask": 49,
			"toTask": 56,
			"xferSize": 2359296.000000,
			"workerId": 65,
			"guid": 59,
			"counter": 1,
			"readyTime": 60.808998,
			"startTime": 60.808998,
			"computeTime": 0.471859
		}, 
		{
			"type": "intra-communication",
			"node":0,
			"commid": 22,
			"fromWorker": 0,
			"toWorker": 3,
			"fromTask": 50,
			"toTask": 56,
			"xferSize": 2359296.000000,
			"workerId": 129,
			"guid": 60,
			"counter": 1,
			"readyTime": 60.808998,
			"startTime": 60.808998,
			"computeTime": 0.471859
		}, 
		{
			"type": "intra-communication",
			"node":0,
			"commid": 23,
			"fromWorker": 0,
			"toWorker": 3,
			"fromTask": 51,
			"toTask": 56,
			"xferSize": 2359296.000000,
			"workerId": 193,
			"guid": 61,
			"counter": 1,
			"readyTime": 59.893303,
			"startTime": 59.893303,
			"computeTime": 0.471859
		}, 
		{
			"type": "intra-communication",
			"node":0,
			"commid": 24,
			"fromWorker": 0,
			"toWorker": 3,
			"fromTask": 52,
			"toTask": 56,
			"xferSize": 2359296.000000,
			"workerId": 257,
			"guid": 62,
			"counter": 1,
			"readyTime": 59.893303,
			"startTime": 59.893303,
			"computeTime": 0.471859
		}, 
		{
			"type": "intra-communication",
			"node":0,
			"commid": 25,
			"fromWorker": 0,
			"toWorker": 1,
			"fromTask": 49,
			"toTask": 57,
			"xferSize": 2359296.000000,
			"workerId": 66,
			"guid": 63,
			"counter": 1,
			"readyTime": 60.808998,
			"startTime": 60.808998,
			"computeTime": 0.471859
		}, 
		{
			"type": "intra-communication",
			"node":0,
			"commid": 26,
			"fromWorker": 0,
			"toWorker": 1,
			"fromTask": 50,
			"toTask": 57,
			"xferSize": 2359296.000000,
			"workerId": 130,
			"guid": 64,
			"counter": 1,
			"readyTime": 60.808998,
			"startTime": 60.808998,
			"computeTime": 0.471859
		}, 
		{
			"type": "intra-communication",
			"node":0,
			"commid": 27,
			"fromWorker": 0,
			"toWorker": 1,
			"fromTask": 51,
			"toTask": 57,
			"xferSize": 2359296.000000,
			"workerId": 194,
			"guid": 65,
			"counter": 1,
			"readyTime": 59.893303,
			"startTime": 59.893303,
			"computeTime": 0.471859
		}, 
		{
			"type": "intra-communication",
			"node":0,
			"commid": 28,
			"fromWorker": 0,
			"toWorker": 1,
			"fromTask": 52,
			"toTask": 57,
			"xferSize": 2359296.000000,
			"workerId": 258,
			"guid": 66,
			"counter": 1,
			"readyTime": 59.893303,
			"startTime": 59.893303,
			"computeTime": 0.471859
		}, 
		{
			"type": "intra-communication",
			"node":0,
			"commid": 29,
			"fromWorker": 0,
			"toWorker": 2,
			"fromTask": 49,
			"toTask": 58,
			"xferSize": 2359296.000000,
			"workerId": 67,
			"guid": 67,
			"counter": 1,
			"readyTime": 60.808998,
			"startTime": 60.808998,
			"computeTime": 0.471859
		}, 
		{
			"type": "intra-communication",
			"node":0,
			"commid": 30,
			"fromWorker": 0,
			"toWorker": 2,
			"fromTask": 50,
			"toTask": 58,
			"xferSize": 2359296.000000,
			"workerId": 131,
			"guid": 68,
			"counter": 1,
			"readyTime": 60.808998,
			"startTime": 60.808998,
			"computeTime": 0.471859
		}, 
		{
			"type": "intra-communication",
			"node":0,
			"commid": 31,
			"fromWorker": 0,
			"toWorker": 2,
			"fromTask": 51,
			"toTask": 58,
			"xferSize": 2359296.000000,
			"workerId": 195,
			"guid": 69,
			"counter": 1,
			"readyTime": 59.893303,
			"startTime": 59.893303,
			"computeTime": 0.471859
		}, 
		{
			"type": "intra-communication",
			"node":0,
			"commid": 32,
			"fromWorker": 0,
			"toWorker": 2,
			"fromTask": 52,
			"toTask": 58,
			"xferSize": 2359296.000000,
			"workerId": 259,
			"guid": 70,
			"counter": 1,
			"readyTime": 59.893303,
			"startTime": 59.893303,
			"computeTime": 0.471859
		}, 
		{
			"type": "intra-communication",
			"node":0,
			"commid": 33,
			"fromWorker": 3,
			"toWorker": 0,
			"fromTask": 56,
			"toTask": 71,
			"xferSize": 1048576.000000,
			"workerId": 128,
			"guid": 75,
			"counter": 1,
			"readyTime": 65.158234,
			"startTime": 65.158234,
			"computeTime": 0.209715
		}, 
		{
			"type": "intra-communication",
			"node":0,
			"commid": 34,
			"fromWorker": 1,
			"toWorker": 0,
			"fromTask": 57,
			"toTask": 71,
			"xferSize": 1048576.000000,
			"workerId": 192,
			"guid": 76,
			"counter": 1,
			"readyTime": 65.158234,
			"startTime": 65.158234,
			"computeTime": 0.209715
		}, 
		{
			"type": "intra-communication",
			"node":0,
			"commid": 35,
			"fromWorker": 2,
			"toWorker": 0,
			"fromTask": 58,
			"toTask": 71,
			"xferSize": 1048576.000000,
			"workerId": 256,
			"guid": 77,
			"counter": 1,
			"readyTime": 65.158234,
			"startTime": 65.158234,
			"computeTime": 0.209715
		}, 
		{
			"type": "intra-communication",
			"node":0,
			"commid": 36,
			"fromWorker": 0,
			"toWorker": 2,
			"fromTask": 55,
			"toTask": 72,
			"xferSize": 1048576.000000,
			"workerId": 65,
			"guid": 78,
			"counter": 1,
			"readyTime": 64.686371,
			"startTime": 64.686371,
			"computeTime": 0.209715
		}, 
		{
			"type": "intra-communication",
			"node":0,
			"commid": 37,
			"fromWorker": 3,
			"toWorker": 2,
			"fromTask": 56,
			"toTask": 72,
			"xferSize": 1048576.000000,
			"workerId": 129,
			"guid": 79,
			"counter": 1,
			"readyTime": 65.158234,
			"startTime": 65.158234,
			"computeTime": 0.209715
		}, 
		{
			"type": "intra-communication",
			"node":0,
			"commid": 38,
			"fromWorker": 1,
			"toWorker": 2,
			"fromTask": 57,
			"toTask": 72,
			"xferSize": 1048576.000000,
			"workerId": 193,
			"guid": 80,
			"counter": 1,
			"readyTime": 65.158234,
			"startTime": 65.158234,
			"computeTime": 0.209715
		}, 
		{
			"type": "intra-communication",
			"node":0,
			"commid": 39,
			"fromWorker": 0,
			"toWorker": 1,
			"fromTask": 55,
			"toTask": 73,
			"xferSize": 1048576.000000,
			"workerId": 66,
			"guid": 81,
			"counter": 1,
			"readyTime": 64.686371,
			"startTime": 64.686371,
			"computeTime": 0.209715
		}, 
		{
			"type": "intra-communication",
			"node":0,
			"commid": 40,
			"fromWorker": 3,
			"toWorker": 1,
			"fromTask": 56,
			"toTask": 73,
			"xferSize": 1048576.000000,
			"workerId": 130,
			"guid": 82,
			"counter": 1,
			"readyTime": 65.158234,
			"startTime": 65.158234,
			"computeTime": 0.209715
		}, 
		{
			"type": "intra-communication",
			"node":0,
			"commid": 41,
			"fromWorker": 2,
			"toWorker": 1,
			"fromTask": 58,
			"toTask": 73,
			"xferSize": 1048576.000000,
			"workerId": 258,
			"guid": 83,
			"counter": 1,
			"readyTime": 65.158234,
			"startTime": 65.158234,
			"computeTime": 0.209715
		}, 
		{
			"type": "intra-communication",
			"node":0,
			"commid": 42,
			"fromWorker": 0,
			"toWorker": 3,
			"fromTask": 55,
			"toTask": 74,
			"xferSize": 1048576.000000,
			"workerId": 67,
			"guid": 84,
			"counter": 1,
			"readyTime": 64.686371,
			"startTime": 64.686371,
			"computeTime": 0.209715
		}, 
		{
			"type": "intra-communication",
			"node":0,
			"commid": 43,
			"fromWorker": 1,
			"toWorker": 3,
			"fromTask": 57,
			"toTask": 74,
			"xferSize": 1048576.000000,
			"workerId": 195,
			"guid": 85,
			"counter": 1,
			"readyTime": 65.158234,
			"startTime": 65.158234,
			"computeTime": 0.209715
		}, 
		{
			"type": "intra-communication",
			"node":0,
			"commid": 44,
			"fromWorker": 2,
			"toWorker": 3,
			"fromTask": 58,
			"toTask": 74,
			"xferSize": 1048576.000000,
			"workerId": 259,
			"guid": 86,
			"counter": 1,
			"readyTime": 65.158234,
			"startTime": 65.158234,
			"computeTime": 0.209715
		}, 
		{
			"type": "intra-communication",
			"node":0,
			"commid": 45,
			"fromWorker": 0,
			"toWorker": 3,
			"fromTask": 71,
			"toTask": 87,
			"xferSize": 1048576.000000,
			"workerId": 64,
			"guid": 91,
			"counter": 1,
			"readyTime": 67.002220,
			"startTime": 67.002220,
			"computeTime": 0.209715
		}, 
		{
			"type": "intra-communication",
			"node":0,
			"commid": 46,
			"fromWorker": 2,
			"toWorker": 3,
			"fromTask": 72,
			"toTask": 87,
			"xferSize": 1048576.000000,
			"workerId": 128,
			"guid": 92,
			"counter": 1,
			"readyTime": 67.002220,
			"startTime": 67.002220,
			"computeTime": 0.209715
		}, 
		{
			"type": "intra-communication",
			"node":0,
			"commid": 47,
			"fromWorker": 1,
			"toWorker": 3,
			"fromTask": 73,
			"toTask": 87,
			"xferSize": 1048576.000000,
			"workerId": 192,
			"guid": 93,
			"counter": 1,
			"readyTime": 67.002220,
			"startTime": 67.002220,
			"computeTime": 0.209715
		}, 
		{
			"type": "intra-communication",
			"node":0,
			"commid": 48,
			"fromWorker": 0,
			"toWorker": 2,
			"fromTask": 71,
			"toTask": 88,
			"xferSize": 1048576.000000,
			"workerId": 65,
			"guid": 94,
			"counter": 1,
			"readyTime": 67.002220,
			"startTime": 67.002220,
			"computeTime": 0.209715
		}, 
		{
			"type": "intra-communication",
			"node":0,
			"commid": 49,
			"fromWorker": 1,
			"toWorker": 2,
			"fromTask": 73,
			"toTask": 88,
			"xferSize": 1048576.000000,
			"workerId": 193,
			"guid": 95,
			"counter": 1,
			"readyTime": 67.002220,
			"startTime": 67.002220,
			"computeTime": 0.209715
		}, 
		{
			"type": "intra-communication",
			"node":0,
			"commid": 50,
			"fromWorker": 3,
			"toWorker": 2,
			"fromTask": 74,
			"toTask": 88,
			"xferSize": 1048576.000000,
			"workerId": 257,
			"guid": 96,
			"counter": 1,
			"readyTime": 67.002220,
			"startTime": 67.002220,
			"computeTime": 0.209715
		}, 
		{
			"type": "intra-communication",
			"node":0,
			"commid": 51,
			"fromWorker": 0,
			"toWorker": 2,
			"fromTask": 71,
			"toTask": 89,
			"xferSize": 1048576.000000,
			"workerId": 66,
			"guid": 97,
			"counter": 1,
			"readyTime": 67.002220,
			"startTime": 67.002220,
			"computeTime": 0.209715
		}, 
		{
			"type": "intra-communication",
			"node":0,
			"commid": 52,
			"fromWorker": 1,
			"toWorker": 2,
			"fromTask": 73,
			"toTask": 89,
			"xferSize": 1048576.000000,
			"workerId": 194,
			"guid": 98,
			"counter": 1,
			"readyTime": 67.002220,
			"startTime": 67.002220,
			"computeTime": 0.209715
		}, 
		{
			"type": "intra-communication",
			"node":0,
			"commid": 53,
			"fromWorker": 3,
			"toWorker": 2,
			"fromTask": 74,
			"toTask": 89,
			"xferSize": 1048576.000000,
			"workerId": 258,
			"guid": 99,
			"counter": 1,
			"readyTime": 67.002220,
			"startTime": 67.002220,
			"computeTime": 0.209715
		}, 
		{
			"type": "intra-communication",
			"node":0,
			"commid": 54,
			"fromWorker": 0,
			"toWorker": 1,
			"fromTask": 71,
			"toTask": 90,
			"xferSize": 1048576.000000,
			"workerId": 67,
			"guid": 100,
			"counter": 1,
			"readyTime": 67.002220,
			"startTime": 67.002220,
			"computeTime": 0.209715
		}, 
		{
			"type": "intra-communication",
			"node":0,
			"commid": 55,
			"fromWorker": 2,
			"toWorker": 1,
			"fromTask": 72,
			"toTask": 90,
			"xferSize": 1048576.000000,
			"workerId": 131,
			"guid": 101,
			"counter": 1,
			"readyTime": 67.002220,
			"startTime": 67.002220,
			"computeTime": 0.209715
		}, 
		{
			"type": "intra-communication",
			"node":0,
			"commid": 56,
			"fromWorker": 3,
			"toWorker": 1,
			"fromTask": 74,
			"toTask": 90,
			"xferSize": 1048576.000000,
			"workerId": 259,
			"guid": 102,
			"counter": 1,
			"readyTime": 67.002220,
			"startTime": 67.002220,
			"computeTime": 0.209715
		}, 
		{
			"type": "intra-communication",
			"node":0,
			"commid": 0,
			"fromWorker": 0,
			"toWorker": 1,
			"fromTask": 90,
			"toTask": 104,
			"xferSize": 278784.000000,
			"workerId": 66,
			"guid": 103,
			"counter": 0,
			"readyTime": 67.694679,
			"startTime": 67.694679,
			"computeTime": 0.055757
		}, 
		{
			"type": "intra-communication",
			"node":0,
			"commid": 1,
			"fromWorker": 0,
			"toWorker": 1,
			"fromTask": 103,
			"toTask": 105,
			"xferSize": 3686400.000000,
			"workerId": 66,
			"guid": 104,
			"counter": 0,
			"readyTime": 67.750435,
			"startTime": 67.750435,
			"computeTime": 0.737280
		}, 
		{
			"type": "intra-communication",
			"node":0,
			"commid": 2,
			"fromWorker": 0,
			"toWorker": 1,
			"fromTask": 104,
			"toTask": 106,
			"xferSize": 5308416.000000,
			"workerId": 66,
			"guid": 105,
			"counter": 0,
			"readyTime": 68.487717,
			"startTime": 68.487717,
			"computeTime": 1.061683
		}, 
		{
			"type": "intra-communication",
			"node":0,
			"commid": 3,
			"fromWorker": 0,
			"toWorker": 1,
			"fromTask": 105,
			"toTask": 107,
			"xferSize": 3538944.000000,
			"workerId": 66,
			"guid": 106,
			"counter": 0,
			"readyTime": 69.549400,
			"startTime": 69.549400,
			"computeTime": 0.707789
		}, 
		{
			"type": "intra-communication",
			"node":0,
			"commid": 4,
			"fromWorker": 0,
			"toWorker": 1,
			"fromTask": 106,
			"toTask": -1811655600,
			"xferSize": 4718592.000000,
			"workerId": 66,
			"guid": 107,
			"counter": 0,
			"readyTime": 70.257187,
			"startTime": 70.257187,
			"computeTime": 0.943718
		} 
	],
	"edges": [
		[0, 4],
		[1, 5],
		[2, 6],
		[3, 7],
		[4, 12],
		[12, 8],
		[5, 13],
		[13, 9],
		[6, 14],
		[14, 10],
		[7, 11],
		[8, 15],
		[9, 19],
		[19, 16],
		[10, 17],
		[11, 20],
		[20, 18],
		[15, 25],
		[25, 21],
		[16, 26],
		[26, 22],
		[17, 27],
		[27, 23],
		[18, 28],
		[28, 24],
		[21, 33],
		[33, 29],
		[22, 34],
		[34, 30],
		[23, 35],
		[35, 31],
		[24, 36],
		[36, 32],
		[29, 41],
		[41, 37],
		[30, 42],
		[42, 38],
		[31, 43],
		[43, 39],
		[32, 44],
		[44, 40],
		[37, 47],
		[47, 45],
		[38, 45],
		[39, 48],
		[48, 46],
		[40, 46],
		[45, 49],
		[45, 50],
		[46, 53],
		[53, 51],
		[46, 54],
		[54, 52],
		[49, 55],
		[50, 55],
		[51, 55],
		[52, 55],
		[49, 59],
		[59, 56],
		[50, 60],
		[60, 56],
		[51, 61],
		[61, 56],
		[52, 62],
		[62, 56],
		[49, 63],
		[63, 57],
		[50, 64],
		[64, 57],
		[51, 65],
		[65, 57],
		[52, 66],
		[66, 57],
		[49, 67],
		[67, 58],
		[50, 68],
		[68, 58],
		[51, 69],
		[69, 58],
		[52, 70],
		[70, 58],
		[55, 71],
		[56, 75],
		[75, 71],
		[57, 76],
		[76, 71],
		[58, 77],
		[77, 71],
		[55, 78],
		[78, 72],
		[56, 79],
		[79, 72],
		[57, 80],
		[80, 72],
		[58, 72],
		[55, 81],
		[81, 73],
		[56, 82],
		[82, 73],
		[57, 73],
		[58, 83],
		[83, 73],
		[55, 84],
		[84, 74],
		[56, 74],
		[57, 85],
		[85, 74],
		[58, 86],
		[86, 74],
		[71, 91],
		[91, 87],
		[72, 92],
		[92, 87],
		[73, 93],
		[93, 87],
		[74, 87],
		[71, 94],
		[94, 88],
		[72, 88],
		[73, 95],
		[95, 88],
		[74, 96],
		[96, 88],
		[71, 97],
		[97, 89],
		[72, 89],
		[73, 98],
		[98, 89],
		[74, 99],
		[99, 89],
		[71, 100],
		[100, 90],
		[72, 101],
		[101, 90],
		[73, 90],
		[74, 102],
		[102, 90],
		[90, 103],
		[103, 104],
		[104, 105],
		[105, 106],
		[106, 107]
	]
}
